clippynote/__init__.py
clippynote/__main__.py
clippynote/cli.py
clippynote/note.py
clippynote-2.1.1.dist-info/LICENSE
clippynote-2.1.1.dist-info/METADATA
clippynote-2.1.1.dist-info/WHEEL
clippynote-2.1.1.dist-info/entry_points.txt
clippynote-2.1.1.dist-info/top_level.txt
clippynote-2.1.1.dist-info/RECORD
