Metadata-Version: 2.1
Name: clippynote
Version: 2.1.1
Summary: A simple CLI for taking notes
Home-page: https://github.com/ccrsxx/clippynote
Author: ccrsxx
Author-email: aminrisal@gmail.com
Project-URL: Bug Tracker, https://github.com/ccrsxx/clippynote/issues
Classifier: Programming Language :: Python :: 3
Classifier: License :: OSI Approved :: MIT License
Classifier: Operating System :: OS Independent
Requires-Python: >=3.6
License-File: LICENSE
Requires-Dist: pyperclip
